py_websites_scraper/__init__.py
py_websites_scraper/scraper.py
py_websites_scraper-0.1.2.1.dist-info/METADATA
py_websites_scraper-0.1.2.1.dist-info/WHEEL
py_websites_scraper-0.1.2.1.dist-info/licenses/LICENSE
py_websites_scraper-0.1.2.1.dist-info/RECORD
