Metadata-Version: 2.4
Name: py-websites-scraper
Version: 0.1.2.1
Summary: Web scraper using aiohttp for efficient scraping of multiple URLs with ease
Project-URL: Homepage, https://github.com/hilmanski/py-websites-scraper
Project-URL: Issues, https://github.com/hilmanski/py-websites-scraper
Author-email: Hilman Ramadhan <hilmanhgb@gmail.com>
License: MIT
License-File: LICENSE
Requires-Python: >=3.8
Requires-Dist: aiohttp>=3.12.2
Requires-Dist: readability-lxml>=0.8.4
Provides-Extra: dev
Requires-Dist: black; extra == 'dev'
Requires-Dist: isort; extra == 'dev'
Requires-Dist: pytest; extra == 'dev'
